gard/__init__.py
gard/diseases.trimmed.json
gard-0.0.3.dist-info/LICENSE
gard-0.0.3.dist-info/METADATA
gard-0.0.3.dist-info/WHEEL
gard-0.0.3.dist-info/top_level.txt
gard-0.0.3.dist-info/RECORD
