Metadata-Version: 2.1
Name: gard
Version: 0.0.3
Summary: GARD ID to URL
Author-email: Steven Tang <stang5@ualberta.ca>
Project-URL: Homepage, https://github.com/BIOIN-401-Project-8/gard
Project-URL: Bug Tracker, https://github.com/BIOIN-401-Project-8/gard/issues
Classifier: Programming Language :: Python :: 3
Classifier: License :: OSI Approved :: MIT License
Classifier: Operating System :: OS Independent
Requires-Python: >=3.10
License-File: LICENSE
Provides-Extra: test
Requires-Dist: pytest ; extra == 'test'
